PWBM_Cloud_Utils/__init__.py
PWBM_Cloud_Utils/api_functions.py
PWBM_Cloud_Utils/cloud_main.py
PWBM_Cloud_Utils/cloud_utils.py
PWBM_Cloud_Utils/entities.py
PWBM_Cloud_Utils/file_manager.py
PWBM_Cloud_Utils/io_base.py
PWBM_Cloud_Utils/io_config.py
PWBM_Cloud_Utils/io_reader.py
PWBM_Cloud_Utils/io_writer.py
PWBM_Cloud_Utils/scripting_functions.py
tests/__init__.py
tests/helpers_testing.py
tests/test_cache.py
tests/test_cloud_main.py
tests/test_cloud_utils.py
tests/test_config.py
tests/test_io_base.py
tests/test_local_file_manager.py
tests/test_local_reader.py
tests/test_local_writer.py
tests/test_s3_file_manager.py
tests/test_s3_reader.py
tests/test_s3_writer.py
tests/test_scripting.py
tests/data/Person.py
PWBM_Cloud_Utils-0.1.5.dist-info/LICENSE
PWBM_Cloud_Utils-0.1.5.dist-info/METADATA
PWBM_Cloud_Utils-0.1.5.dist-info/WHEEL
PWBM_Cloud_Utils-0.1.5.dist-info/top_level.txt
PWBM_Cloud_Utils-0.1.5.dist-info/RECORD
