Metadata-Version: 2.1
Name: PWBM_Cloud_Utils
Version: 0.1.5
Summary: connect to read/write data to s3
Author-email: "Yunye Jiang, Mariko Paulson, Chris Palenchar" <yunyej@wharton.upenn.edu>
Project-URL: Homepage, https://github.com/PennWhartonBudgetModel/PWBM_Cloud_Utils
Project-URL: Bug Tracker, https://github.com/PennWhartonBudgetModel/PWBM_Cloud_Utils/issues
Classifier: Programming Language :: Python :: 3
Classifier: License :: OSI Approved :: MIT License
Classifier: Operating System :: OS Independent
Requires-Python: >=3.10
License-File: LICENSE
Requires-Dist: boto3
Requires-Dist: pandas
Requires-Dist: python-dotenv
Requires-Dist: requests
Requires-Dist: pyarrow
Requires-Dist: typing-extensions
Requires-Dist: s3fs >=2023.3.0
